airflow/providers/apache/hive/__init__.py
airflow/providers/apache/hive/example_dags/__init__.py
airflow/providers/apache/hive/example_dags/example_twitter_dag.py
airflow/providers/apache/hive/hooks/__init__.py
airflow/providers/apache/hive/hooks/hive.py
airflow/providers/apache/hive/operators/__init__.py
airflow/providers/apache/hive/operators/hive.py
airflow/providers/apache/hive/operators/hive_stats.py
airflow/providers/apache/hive/sensors/__init__.py
airflow/providers/apache/hive/sensors/hive_partition.py
airflow/providers/apache/hive/sensors/metastore_partition.py
airflow/providers/apache/hive/sensors/named_hive_partition.py
airflow/providers/apache/hive/transfers/__init__.py
airflow/providers/apache/hive/transfers/hive_to_mysql.py
airflow/providers/apache/hive/transfers/hive_to_samba.py
airflow/providers/apache/hive/transfers/mssql_to_hive.py
airflow/providers/apache/hive/transfers/mysql_to_hive.py
airflow/providers/apache/hive/transfers/s3_to_hive.py
airflow/providers/apache/hive/transfers/vertica_to_hive.py
apache_airflow_backport_providers_apache_hive-2021.3.3.dist-info/LICENSE
apache_airflow_backport_providers_apache_hive-2021.3.3.dist-info/METADATA
apache_airflow_backport_providers_apache_hive-2021.3.3.dist-info/NOTICE
apache_airflow_backport_providers_apache_hive-2021.3.3.dist-info/WHEEL
apache_airflow_backport_providers_apache_hive-2021.3.3.dist-info/top_level.txt
apache_airflow_backport_providers_apache_hive-2021.3.3.dist-info/RECORD
